[{"$insert_id": "183fa091-6d8f-45fb-b62f-e3ef469ea80e", "$insert_key": null, "$schema": null, "adid": null, "amplitude_attribution_ids": null, "amplitude_event_type": null, "amplitude_id": 112071011574, "app": 100011471, "city": "Singapore", "client_event_time": "2026-04-29 22:49:31.749000", "client_upload_time": "2026-04-29 22:49:34.555000", "country": "Singapore", "data": {"path": "/2/httpapi", "group_first_event": {}, "group_ids": {}}, "data_type": "event", "device_brand": null, "device_carrier": null, "device_family": "Android", "device_id": "b3d4f77f-0c58-4a93-bb6f-901b9d03e4ee", "device_manufacturer": null, "device_model": null, "device_type": "Android", "dma": null, "event_id": 1, "event_properties": {}, "event_time": "2026-04-29 22:49:31.749000", "event_type": "session_start", "global_user_properties": null, "group_properties": {}, "groups": {}, "idfa": null, "ip_address": "47.128.49.44", "is_attribution_event": null, "language": "English", "library": "amplitude-ts/2.16.1", "location_lat": null, "location_lng": null, "os_name": "Bytespider", "os_version": null, "partner_id": null, "paying": null, "plan": {}, "platform": "Web", "processed_time": "2026-04-29 22:49:35.924000", "region": null, "sample_rate": null, "server_received_time": "2026-04-29 22:49:34.555000", "server_upload_time": "2026-04-29 22:49:34.558000", "session_id": 1777502971749, "source_id": null, "start_version": null, "user_creation_time": null, "user_id": null, "user_properties": {"initial_utm_medium": "EMPTY", "initial_referring_domain": "EMPTY", "initial_utm_content": "EMPTY", "initial_utm_campaign": "EMPTY", "initial_li_fat_id": "EMPTY", "initial_twclid": "EMPTY", "initial_gclid": "EMPTY", "initial_utm_source": "EMPTY", "initial_dclid": "EMPTY", "initial_wbraid": "EMPTY", "initial_fbclid": "EMPTY", "initial_rtd_cid": "EMPTY", "initial_utm_id": "EMPTY", "initial_referrer": "EMPTY", "initial_gbraid": "EMPTY", "initial_utm_term": "EMPTY", "initial_msclkid": "EMPTY", "initial_ttclid": "EMPTY", "initial_ko_click_id": "EMPTY"}, "uuid": "aa4e7275-0905-429c-baeb-ed35057d69e7", "version_name": null}, {"$insert_id": "39831809-a5f5-42ab-b267-4c997fb48953", "$insert_key": null, "$schema": null, "adid": null, "amplitude_attribution_ids": null, "amplitude_event_type": null, "amplitude_id": 112071011574, "app": 100011471, "city": "Singapore", "client_event_time": "2026-04-29 22:49:31.756000", "client_upload_time": "2026-04-29 22:49:34.555000", "country": "Singapore", "data": {"path": "/2/httpapi", "group_first_event": {}, "group_ids": {}}, "data_type": "event", "device_brand": null, "device_carrier": null, "device_family": "Android", "device_id": "b3d4f77f-0c58-4a93-bb6f-901b9d03e4ee", "device_manufacturer": null, "device_model": null, "device_type": "Android", "dma": null, "event_id": 2, "event_properties": {"[Amplitude] Page URL": "https://www.theinformationlab.co.uk/community/blog/tableau-mcp-starter-kit/", "[Amplitude] Page Counter": 1, "[Amplitude] Page Domain": "www.theinformationlab.co.uk", "[Amplitude] Page Path": "/community/blog/tableau-mcp-starter-kit/", "[Amplitude] Page Title": "Start Building AI Applications with The Tableau MCP Starter Kit - The Information Lab", "[Amplitude] Page Location": "https://www.theinformationlab.co.uk/community/blog/tableau-mcp-starter-kit/"}, "event_time": "2026-04-29 22:49:31.756000", "event_type": "[Amplitude] Page Viewed", "global_user_properties": null, "group_properties": {}, "groups": {}, "idfa": null, "ip_address": "47.128.49.44", "is_attribution_event": null, "language": "English", "library": "amplitude-ts/2.16.1", "location_lat": null, "location_lng": null, "os_name": "Bytespider", "os_version": null, "partner_id": null, "paying": null, "plan": {}, "platform": "Web", "processed_time": "2026-04-29 22:49:35.924000", "region": null, "sample_rate": null, "server_received_time": "2026-04-29 22:49:34.555000", "server_upload_time": "2026-04-29 22:49:34.558000", "session_id": 1777502971749, "source_id": null, "start_version": null, "user_creation_time": null, "user_id": null, "user_properties": {"initial_utm_medium": "EMPTY", "initial_referring_domain": "EMPTY", "initial_utm_content": "EMPTY", "initial_utm_campaign": "EMPTY", "initial_li_fat_id": "EMPTY", "initial_twclid": "EMPTY", "initial_gclid": "EMPTY", "initial_utm_source": "EMPTY", "initial_dclid": "EMPTY", "initial_wbraid": "EMPTY", "initial_fbclid": "EMPTY", "initial_rtd_cid": "EMPTY", "initial_utm_id": "EMPTY", "initial_referrer": "EMPTY", "initial_gbraid": "EMPTY", "initial_utm_term": "EMPTY", "initial_msclkid": "EMPTY", "initial_ttclid": "EMPTY", "initial_ko_click_id": "EMPTY"}, "uuid": "a3668547-9c37-4eca-8595-de332db629e6", "version_name": null}, {"$insert_id": "e0daa7b3-369b-45e3-8742-59109873883c", "$insert_key": null, "$schema": null, "adid": null, "amplitude_attribution_ids": null, "amplitude_event_type": null, "amplitude_id": 112066266868, "app": 100011471, "city": null, "client_event_time": "2026-04-29 22:06:04.835000", "client_upload_time": "2026-04-29 22:06:09.904000", "country": "Singapore", "data": {"path": "/2/httpapi", "group_first_event": {}, "group_ids": {}}, "data_type": "event", "device_brand": null, "device_carrier": null, "device_family": "Windows", "device_id": "8f6efbad-94e1-4d6c-98ef-0e7ac97861e5", "device_manufacturer": null, "device_model": null, "device_type": "Windows", "dma": null, "event_id": 1, "event_properties": {}, "event_time": "2026-04-29 22:06:04.835000", "event_type": "session_start", "global_user_properties": null, "group_properties": {}, "groups": {}, "idfa": null, "ip_address": "43.172.197.121", "is_attribution_event": null, "language": "English", "library": "amplitude-ts/2.16.1", "location_lat": null, "location_lng": null, "os_name": "Chrome", "os_version": "108", "partner_id": null, "paying": null, "plan": {}, "platform": "Web", "processed_time": "2026-04-29 22:06:11.161000", "region": null, "sample_rate": null, "server_received_time": "2026-04-29 22:06:09.904000", "server_upload_time": "2026-04-29 22:06:09.907000", "session_id": 1777500364835, "source_id": null, "start_version": null, "user_creation_time": null, "user_id": null, "user_properties": {"initial_utm_medium": "EMPTY", "initial_referring_domain": "EMPTY", "initial_utm_content": "EMPTY", "initial_utm_campaign": "EMPTY", "initial_li_fat_id": "EMPTY", "initial_twclid": "EMPTY", "initial_gclid": "EMPTY", "initial_utm_source": "EMPTY", "initial_dclid": "EMPTY", "initial_wbraid": "EMPTY", "initial_fbclid": "EMPTY", "initial_rtd_cid": "EMPTY", "initial_utm_id": "EMPTY", "initial_referrer": "EMPTY", "initial_gbraid": "EMPTY", "initial_utm_term": "EMPTY", "initial_msclkid": "EMPTY", "initial_ttclid": "EMPTY", "initial_ko_click_id": "EMPTY"}, "uuid": "4b6e36d5-05bb-4a6d-8ebf-9c835c90ec8c", "version_name": null}, {"$insert_id": "f17dec34-8917-41a7-9fca-f261c947b79c", "$insert_key": null, "$schema": null, "adid": null, "amplitude_attribution_ids": null, "amplitude_event_type": null, "amplitude_id": 109119773059, "app": 100011471, "city": "Oklahoma City", "client_event_time": "2026-03-30 18:24:43.226000", "client_upload_time": "2026-04-29 22:02:33.391000", "country": "United States", "data": {"path": "/2/httpapi", "user_properties_updated": true, "group_first_event": {}, "group_ids": {}}, "data_type": "event", "device_brand": null, "device_carrier": null, "device_family": "Windows", "device_id": "5bd39340-33e5-494b-8b9d-81125c929bc9", "device_manufacturer": null, "device_model": null, "device_type": "Windows", "dma": "Oklahoma City, OK", "event_id": 3, "event_properties": {}, "event_time": "2026-03-30 18:24:43.226000", "event_type": "session_end", "global_user_properties": null, "group_properties": {}, "groups": {}, "idfa": null, "ip_address": "184.185.231.80", "is_attribution_event": null, "language": "English", "library": "amplitude-ts/2.16.1", "location_lat": null, "location_lng": null, "os_name": "Firefox", "os_version": "150", "partner_id": null, "paying": null, "plan": {}, "platform": "Web", "processed_time": "2026-04-29 22:02:35.016000", "region": "Oklahoma", "sample_rate": null, "server_received_time": "2026-04-29 22:02:33.391000", "server_upload_time": "2026-04-29 22:02:33.395000", "session_id": 1774895083223, "source_id": null, "start_version": null, "user_creation_time": null, "user_id": null, "user_properties": {"initial_utm_medium": "EMPTY", "initial_referring_domain": "EMPTY", "initial_utm_content": "EMPTY", "initial_utm_campaign": "EMPTY", "initial_twclid": "EMPTY", "initial_li_fat_id": "EMPTY", "initial_gclid": "EMPTY", "initial_utm_source": "EMPTY", "initial_dclid": "EMPTY", "initial_wbraid": "EMPTY", "initial_fbclid": "EMPTY", "initial_rtd_cid": "EMPTY", "initial_utm_id": "EMPTY", "initial_referrer": "EMPTY", "initial_gbraid": "EMPTY", "initial_utm_term": "EMPTY", "initial_msclkid": "EMPTY", "initial_ttclid": "EMPTY", "initial_ko_click_id": "EMPTY"}, "uuid": "cf7c2401-cd1e-49dd-b756-e8074a4c138c", "version_name": null}, {"$insert_id": "60260f0f-c699-489f-bf99-4db3928371f1", "$insert_key": null, "$schema": null, "adid": null, "amplitude_attribution_ids": null, "amplitude_event_type": null, "amplitude_id": 109119773059, "app": 100011471, "city": "Oklahoma City", "client_event_time": "2026-04-29 22:02:32.013000", "client_upload_time": "2026-04-29 22:02:33.391000", "country": "United States", "data": {"path": "/2/httpapi", "user_properties_updated": true, "group_first_event": {}, "group_ids": {}}, "data_type": "event", "device_brand": null, "device_carrier": null, "device_family": "Windows", "device_id": "5bd39340-33e5-494b-8b9d-81125c929bc9", "device_manufacturer": null, "device_model": null, "device_type": "Windows", "dma": "Oklahoma City, OK", "event_id": 4, "event_properties": {}, "event_time": "2026-04-29 22:02:32.013000", "event_type": "session_start", "global_user_properties": null, "group_properties": {}, "groups": {}, "idfa": null, "ip_address": "184.185.231.80", "is_attribution_event": null, "language": "English", "library": "amplitude-ts/2.16.1", "location_lat": null, "location_lng": null, "os_name": "Firefox", "os_version": "150", "partner_id": null, "paying": null, "plan": {}, "platform": "Web", "processed_time": "2026-04-29 22:02:35.016000", "region": "Oklahoma", "sample_rate": null, "server_received_time": "2026-04-29 22:02:33.391000", "server_upload_time": "2026-04-29 22:02:33.395000", "session_id": 1777500152013, "source_id": null, "start_version": null, "user_creation_time": null, "user_id": null, "user_properties": {"initial_utm_medium": "EMPTY", "initial_referring_domain": "EMPTY", "initial_utm_content": "EMPTY", "initial_utm_campaign": "EMPTY", "initial_twclid": "EMPTY", "initial_li_fat_id": "EMPTY", "initial_gclid": "EMPTY", "initial_utm_source": "EMPTY", "initial_dclid": "EMPTY", "initial_wbraid": "EMPTY", "initial_fbclid": "EMPTY", "initial_rtd_cid": "EMPTY", "initial_utm_id": "EMPTY", "initial_referrer": "EMPTY", "initial_gbraid": "EMPTY", "initial_utm_term": "EMPTY", "initial_msclkid": "EMPTY", "initial_ttclid": "EMPTY", "initial_ko_click_id": "EMPTY"}, "uuid": "c3c03d31-ef68-421f-8a3e-6d3d5c19f53d", "version_name": null}, {"$insert_id": "b6a4bc04-5e80-471f-a506-d0a0ced348c1", "$insert_key": null, "$schema": null, "adid": null, "amplitude_attribution_ids": null, "amplitude_event_type": null, "amplitude_id": 112066266868, "app": 100011471, "city": null, "client_event_time": "2026-04-29 22:06:05.452000", "client_upload_time": "2026-04-29 22:06:09.904000", "country": "Singapore", "data": {"path": "/2/httpapi", "group_first_event": {}, "group_ids": {}}, "data_type": "event", "device_brand": null, "device_carrier": null, "device_family": "Windows", "device_id": "8f6efbad-94e1-4d6c-98ef-0e7ac97861e5", "device_manufacturer": null, "device_model": null, "device_type": "Windows", "dma": null, "event_id": 2, "event_properties": {"[Amplitude] Page URL": "https://www.theinformationlab.co.uk/author/samuel-shurmer/", "[Amplitude] Page Counter": 1, "[Amplitude] Page Domain": "www.theinformationlab.co.uk", "[Amplitude] Page Path": "/author/samuel-shurmer/", "[Amplitude] Page Title": "404 - Connection Error", "[Amplitude] Page Location": "https://www.theinformationlab.co.uk/author/samuel-shurmer/"}, "event_time": "2026-04-29 22:06:05.452000", "event_type": "[Amplitude] Page Viewed", "global_user_properties": null, "group_properties": {}, "groups": {}, "idfa": null, "ip_address": "43.172.197.121", "is_attribution_event": null, "language": "English", "library": "amplitude-ts/2.16.1", "location_lat": null, "location_lng": null, "os_name": "Chrome", "os_version": "108", "partner_id": null, "paying": null, "plan": {}, "platform": "Web", "processed_time": "2026-04-29 22:06:11.161000", "region": null, "sample_rate": null, "server_received_time": "2026-04-29 22:06:09.904000", "server_upload_time": "2026-04-29 22:06:09.907000", "session_id": 1777500364835, "source_id": null, "start_version": null, "user_creation_time": null, "user_id": null, "user_properties": {"initial_utm_medium": "EMPTY", "initial_referring_domain": "EMPTY", "initial_utm_content": "EMPTY", "initial_utm_campaign": "EMPTY", "initial_li_fat_id": "EMPTY", "initial_twclid": "EMPTY", "initial_gclid": "EMPTY", "initial_utm_source": "EMPTY", "initial_dclid": "EMPTY", "initial_wbraid": "EMPTY", "initial_fbclid": "EMPTY", "initial_rtd_cid": "EMPTY", "initial_utm_id": "EMPTY", "initial_referrer": "EMPTY", "initial_gbraid": "EMPTY", "initial_utm_term": "EMPTY", "initial_msclkid": "EMPTY", "initial_ttclid": "EMPTY", "initial_ko_click_id": "EMPTY"}, "uuid": "bcf46e14-254c-4366-890f-a018d8d75e21", "version_name": null}, {"$insert_id": "932fe4b9-759c-4f61-b832-47476bf1aaec", "$insert_key": null, "$schema": null, "adid": null, "amplitude_attribution_ids": null, "amplitude_event_type": null, "amplitude_id": 109119773059, "app": 100011471, "city": "Oklahoma City", "client_event_time": "2026-04-29 22:02:32.031000", "client_upload_time": "2026-04-29 22:02:33.391000", "country": "United States", "data": {"path": "/2/httpapi", "group_first_event": {}, "group_ids": {}}, "data_type": "event", "device_brand": null, "device_carrier": null, "device_family": "Windows", "device_id": "5bd39340-33e5-494b-8b9d-81125c929bc9", "device_manufacturer": null, "device_model": null, "device_type": "Windows", "dma": "Oklahoma City, OK", "event_id": 5, "event_properties": {"[Amplitude] Page URL": "https://www.theinformationlab.co.uk/community/blog/upskill-your-team-with-tableau-public-mcp/", "[Amplitude] Page Counter": 1, "[Amplitude] Page Domain": "www.theinformationlab.co.uk", "[Amplitude] Page Path": "/community/blog/upskill-your-team-with-tableau-public-mcp/", "[Amplitude] Page Title": "Upskill Your Team With Tableau Public MCP - The Information Lab", "[Amplitude] Page Location": "https://www.theinformationlab.co.uk/community/blog/upskill-your-team-with-tableau-public-mcp/"}, "event_time": "2026-04-29 22:02:32.031000", "event_type": "[Amplitude] Page Viewed", "global_user_properties": null, "group_properties": {}, "groups": {}, "idfa": null, "ip_address": "184.185.231.80", "is_attribution_event": null, "language": "English", "library": "amplitude-ts/2.16.1", "location_lat": null, "location_lng": null, "os_name": "Firefox", "os_version": "150", "partner_id": null, "paying": null, "plan": {}, "platform": "Web", "processed_time": "2026-04-29 22:02:35.016000", "region": "Oklahoma", "sample_rate": null, "server_received_time": "2026-04-29 22:02:33.391000", "server_upload_time": "2026-04-29 22:02:33.395000", "session_id": 1777500152013, "source_id": null, "start_version": null, "user_creation_time": null, "user_id": null, "user_properties": {"initial_utm_medium": "EMPTY", "initial_referring_domain": "EMPTY", "initial_utm_content": "EMPTY", "initial_utm_campaign": "EMPTY", "initial_twclid": "EMPTY", "initial_li_fat_id": "EMPTY", "initial_gclid": "EMPTY", "initial_utm_source": "EMPTY", "initial_dclid": "EMPTY", "initial_wbraid": "EMPTY", "initial_fbclid": "EMPTY", "initial_rtd_cid": "EMPTY", "initial_utm_id": "EMPTY", "initial_referrer": "EMPTY", "initial_gbraid": "EMPTY", "initial_utm_term": "EMPTY", "initial_msclkid": "EMPTY", "initial_ttclid": "EMPTY", "initial_ko_click_id": "EMPTY"}, "uuid": "508fddb4-c4e4-43e4-a0b0-cbd465618ca5", "version_name": null}, {"$insert_id": "6bc3b396-1f5b-4483-b1e8-13f0603868bc", "$insert_key": null, "$schema": null, "adid": null, "amplitude_attribution_ids": null, "amplitude_event_type": null, "amplitude_id": 112055801661, "app": 100011471, "city": "Canton", "client_event_time": "2026-04-29 20:37:06.972000", "client_upload_time": "2026-04-29 22:41:25.873000", "country": "United States", "data": {"path": "/2/httpapi", "group_first_event": {}, "group_ids": {}}, "data_type": "event", "device_brand": null, "device_carrier": null, "device_family": "Windows", "device_id": "ca5361c6-00a8-4861-9664-c06b74e4fd56", "device_manufacturer": null, "device_model": null, "device_type": "Windows", "dma": "Boston, MA-Manchester, NH", "event_id": 3, "event_properties": {}, "event_time": "2026-04-29 20:37:06.972000", "event_type": "session_end", "global_user_properties": null, "group_properties": {}, "groups": {}, "idfa": null, "ip_address": "108.7.36.197", "is_attribution_event": null, "language": "English", "library": "amplitude-ts/2.16.1", "location_lat": null, "location_lng": null, "os_name": "Chrome", "os_version": "147", "partner_id": null, "paying": null, "plan": {}, "platform": "Web", "processed_time": "2026-04-29 22:41:27.284000", "region": "Massachusetts", "sample_rate": null, "server_received_time": "2026-04-29 22:41:25.873000", "server_upload_time": "2026-04-29 22:41:25.878000", "session_id": 1777495026966, "source_id": null, "start_version": null, "user_creation_time": null, "user_id": null, "user_properties": {"initial_utm_medium": "EMPTY", "initial_referring_domain": "www.google.com", "initial_utm_content": "EMPTY", "initial_utm_campaign": "EMPTY", "initial_twclid": "EMPTY", "initial_li_fat_id": "EMPTY", "referrer": "https://www.google.com/", "initial_gclid": "EMPTY", "initial_utm_source": "EMPTY", "initial_dclid": "EMPTY", "initial_wbraid": "EMPTY", "initial_fbclid": "EMPTY", "initial_rtd_cid": "EMPTY", "initial_utm_id": "EMPTY", "initial_referrer": "https://www.google.com/", "initial_gbraid": "EMPTY", "initial_utm_term": "EMPTY", "initial_msclkid": "EMPTY", "initial_ttclid": "EMPTY", "initial_ko_click_id": "EMPTY", "referring_domain": "www.google.com"}, "uuid": "b929c0f0-69fa-4a0f-a415-e9dd55763e9b", "version_name": null}, {"$insert_id": "5d02e3da-c55b-4209-8be8-f5c55d0a1242", "$insert_key": null, "$schema": null, "adid": null, "amplitude_attribution_ids": null, "amplitude_event_type": null, "amplitude_id": 112066085375, "app": 100011471, "city": "Camarillo", "client_event_time": "2026-04-29 22:04:24.586000", "client_upload_time": "2026-04-29 22:04:26.209000", "country": "United States", "data": {"path": "/2/httpapi", "group_first_event": {}, "group_ids": {}}, "data_type": "event", "device_brand": null, "device_carrier": null, "device_family": "Windows", "device_id": "9037b436-93a0-4907-930b-a50b2c664d1e", "device_manufacturer": null, "device_model": null, "device_type": "Windows", "dma": "Los Angeles, CA", "event_id": 1, "event_properties": {}, "event_time": "2026-04-29 22:04:24.586000", "event_type": "session_start", "global_user_properties": null, "group_properties": {}, "groups": {}, "idfa": null, "ip_address": "209.129.115.6", "is_attribution_event": null, "language": "English", "library": "amplitude-ts/2.16.1", "location_lat": null, "location_lng": null, "os_name": "Chrome", "os_version": "147", "partner_id": null, "paying": null, "plan": {}, "platform": "Web", "processed_time": "2026-04-29 22:04:27.775000", "region": "California", "sample_rate": null, "server_received_time": "2026-04-29 22:04:26.209000", "server_upload_time": "2026-04-29 22:04:26.214000", "session_id": 1777500264586, "source_id": null, "start_version": null, "user_creation_time": null, "user_id": null, "user_properties": {"initial_utm_medium": "EMPTY", "initial_referring_domain": "EMPTY", "initial_utm_content": "EMPTY", "initial_utm_campaign": "EMPTY", "initial_li_fat_id": "EMPTY", "initial_twclid": "EMPTY", "initial_gclid": "EMPTY", "initial_utm_source": "EMPTY", "initial_dclid": "EMPTY", "initial_wbraid": "EMPTY", "initial_fbclid": "EMPTY", "initial_rtd_cid": "EMPTY", "initial_utm_id": "EMPTY", "initial_referrer": "EMPTY", "initial_gbraid": "EMPTY", "initial_utm_term": "EMPTY", "initial_msclkid": "EMPTY", "initial_ttclid": "EMPTY", "initial_ko_click_id": "EMPTY"}, "uuid": "917662bb-fac8-4c9c-a71a-dfa44f01505a", "version_name": null}, {"$insert_id": "357126ad-d439-4d98-9949-14924b300f4f", "$insert_key": null, "$schema": null, "adid": null, "amplitude_attribution_ids": null, "amplitude_event_type": null, "amplitude_id": 112066683664, "app": 100011471, "city": "Las Cruces", "client_event_time": "2026-04-29 22:09:54.937000", "client_upload_time": "2026-04-29 22:09:55.946000", "country": "United States", "data": {"path": "/2/httpapi", "group_first_event": {}, "group_ids": {}}, "data_type": "event", "device_brand": null, "device_carrier": null, "device_family": "Windows", "device_id": "454c5006-8621-43f5-a7d9-13136bf3fab9", "device_manufacturer": null, "device_model": null, "device_type": "Windows", "dma": "El Paso, TX", "event_id": 1, "event_properties": {}, "event_time": "2026-04-29 22:09:54.937000", "event_type": "session_start", "global_user_properties": null, "group_properties": {}, "groups": {}, "idfa": null, "ip_address": "98.249.93.163", "is_attribution_event": null, "language": "English", "library": "amplitude-ts/2.16.1", "location_lat": null, "location_lng": null, "os_name": "Chrome", "os_version": "147", "partner_id": null, "paying": null, "plan": {}, "platform": "Web", "processed_time": "2026-04-29 22:09:57.396000", "region": "New Mexico", "sample_rate": null, "server_received_time": "2026-04-29 22:09:55.946000", "server_upload_time": "2026-04-29 22:09:55.948000", "session_id": 1777500594937, "source_id": null, "start_version": null, "user_creation_time": null, "user_id": null, "user_properties": {"initial_utm_medium": "EMPTY", "initial_referring_domain": "www.google.com", "initial_utm_content": "EMPTY", "initial_utm_campaign": "EMPTY", "initial_li_fat_id": "EMPTY", "initial_twclid": "EMPTY", "referrer": "https://www.google.com/", "initial_gclid": "EMPTY", "initial_utm_source": "EMPTY", "initial_dclid": "EMPTY", "initial_wbraid": "EMPTY", "initial_fbclid": "EMPTY", "initial_rtd_cid": "EMPTY", "initial_utm_id": "EMPTY", "initial_referrer": "https://www.google.com/", "initial_gbraid": "EMPTY", "initial_utm_term": "EMPTY", "initial_msclkid": "EMPTY", "initial_ttclid": "EMPTY", "initial_ko_click_id": "EMPTY", "referring_domain": "www.google.com"}, "uuid": "de1791b5-9bb5-4f6d-9cbf-b345da52ff0a", "version_name": null}, {"$insert_id": "50922efb-083b-41c0-abea-658f3ecaa282", "$insert_key": null, "$schema": null, "adid": null, "amplitude_attribution_ids": null, "amplitude_event_type": null, "amplitude_id": 112055801661, "app": 100011471, "city": "Canton", "client_event_time": "2026-04-29 22:41:24.740000", "client_upload_time": "2026-04-29 22:41:25.873000", "country": "United States", "data": {"path": "/2/httpapi", "group_first_event": {}, "group_ids": {}}, "data_type": "event", "device_brand": null, "device_carrier": null, "device_family": "Windows", "device_id": "ca5361c6-00a8-4861-9664-c06b74e4fd56", "device_manufacturer": null, "device_model": null, "device_type": "Windows", "dma": "Boston, MA-Manchester, NH", "event_id": 4, "event_properties": {"[Amplitude] Session Replay ID": "ca5361c6-00a8-4861-9664-c06b74e4fd56/1777502484740"}, "event_time": "2026-04-29 22:41:24.740000", "event_type": "session_start", "global_user_properties": null, "group_properties": {}, "groups": {}, "idfa": null, "ip_address": "108.7.36.197", "is_attribution_event": null, "language": "English", "library": "amplitude-ts/2.16.1", "location_lat": null, "location_lng": null, "os_name": "Chrome", "os_version": "147", "partner_id": null, "paying": null, "plan": {}, "platform": "Web", "processed_time": "2026-04-29 22:41:27.284000", "region": "Massachusetts", "sample_rate": null, "server_received_time": "2026-04-29 22:41:25.873000", "server_upload_time": "2026-04-29 22:41:25.878000", "session_id": 1777502484740, "source_id": null, "start_version": null, "user_creation_time": null, "user_id": null, "user_properties": {"initial_utm_medium": "EMPTY", "initial_referring_domain": "www.google.com", "initial_utm_content": "EMPTY", "initial_utm_campaign": "EMPTY", "initial_twclid": "EMPTY", "initial_li_fat_id": "EMPTY", "referrer": "https://www.google.com/", "initial_gclid": "EMPTY", "initial_utm_source": "EMPTY", "initial_dclid": "EMPTY", "initial_wbraid": "EMPTY", "initial_fbclid": "EMPTY", "initial_rtd_cid": "EMPTY", "initial_utm_id": "EMPTY", "initial_referrer": "https://www.google.com/", "initial_gbraid": "EMPTY", "initial_utm_term": "EMPTY", "initial_msclkid": "EMPTY", "initial_ttclid": "EMPTY", "initial_ko_click_id": "EMPTY", "referring_domain": "www.google.com"}, "uuid": "5778b21b-9b08-4a37-b5c5-912b550f543c", "version_name": null}, {"$insert_id": "6071e70a-dd4b-4557-a5ca-e8d6ba7e1474", "$insert_key": null, "$schema": null, "adid": null, "amplitude_attribution_ids": null, "amplitude_event_type": null, "amplitude_id": 112066683664, "app": 100011471, "city": "Las Cruces", "client_event_time": "2026-04-29 22:09:54.941000", "client_upload_time": "2026-04-29 22:09:55.946000", "country": "United States", "data": {"path": "/2/httpapi", "group_first_event": {}, "group_ids": {}}, "data_type": "event", "device_brand": null, "device_carrier": null, "device_family": "Windows", "device_id": "454c5006-8621-43f5-a7d9-13136bf3fab9", "device_manufacturer": null, "device_model": null, "device_type": "Windows", "dma": "El Paso, TX", "event_id": 2, "event_properties": {"[Amplitude] Page URL": "https://www.theinformationlab.co.uk/community/blog/how-to-set-up-tabpy-in-tableau/", "referrer": "https://www.google.com/", "[Amplitude] Page Counter": 1, "[Amplitude] Page Domain": "www.theinformationlab.co.uk", "[Amplitude] Page Path": "/community/blog/how-to-set-up-tabpy-in-tableau/", "[Amplitude] Page Title": "How to set up TabPy in Tableau - The Information Lab", "[Amplitude] Page Location": "https://www.theinformationlab.co.uk/community/blog/how-to-set-up-tabpy-in-tableau/", "referring_domain": "www.google.com"}, "event_time": "2026-04-29 22:09:54.941000", "event_type": "[Amplitude] Page Viewed", "global_user_properties": null, "group_properties": {}, "groups": {}, "idfa": null, "ip_address": "98.249.93.163", "is_attribution_event": null, "language": "English", "library": "amplitude-ts/2.16.1", "location_lat": null, "location_lng": null, "os_name": "Chrome", "os_version": "147", "partner_id": null, "paying": null, "plan": {}, "platform": "Web", "processed_time": "2026-04-29 22:09:57.396000", "region": "New Mexico", "sample_rate": null, "server_received_time": "2026-04-29 22:09:55.946000", "server_upload_time": "2026-04-29 22:09:55.948000", "session_id": 1777500594937, "source_id": null, "start_version": null, "user_creation_time": null, "user_id": null, "user_properties": {"initial_utm_medium": "EMPTY", "initial_referring_domain": "www.google.com", "initial_utm_content": "EMPTY", "initial_utm_campaign": "EMPTY", "initial_li_fat_id": "EMPTY", "initial_twclid": "EMPTY", "referrer": "https://www.google.com/", "initial_gclid": "EMPTY", "initial_utm_source": "EMPTY", "initial_dclid": "EMPTY", "initial_wbraid": "EMPTY", "initial_fbclid": "EMPTY", "initial_rtd_cid": "EMPTY", "initial_utm_id": "EMPTY", "initial_referrer": "https://www.google.com/", "initial_gbraid": "EMPTY", "initial_utm_term": "EMPTY", "initial_msclkid": "EMPTY", "initial_ttclid": "EMPTY", "initial_ko_click_id": "EMPTY", "referring_domain": "www.google.com"}, "uuid": "a898a2af-efc1-4fd5-b4cc-3efce5c5c4af", "version_name": null}, {"$insert_id": "52d23d6c-b372-4386-961b-e02ae9e6882a", "$insert_key": null, "$schema": null, "adid": null, "amplitude_attribution_ids": null, "amplitude_event_type": null, "amplitude_id": 112066085375, "app": 100011471, "city": "Camarillo", "client_event_time": "2026-04-29 22:04:24.596000", "client_upload_time": "2026-04-29 22:04:26.209000", "country": "United States", "data": {"path": "/2/httpapi", "group_first_event": {}, "group_ids": {}}, "data_type": "event", "device_brand": null, "device_carrier": null, "device_family": "Windows", "device_id": "9037b436-93a0-4907-930b-a50b2c664d1e", "device_manufacturer": null, "device_model": null, "device_type": "Windows", "dma": "Los Angeles, CA", "event_id": 2, "event_properties": {"[Amplitude] Page URL": "https://www.theinformationlab.co.uk/community/blog/using-dynamic-zone-visibility-for-show-hide-buttons/", "[Amplitude] Page Counter": 1, "[Amplitude] Page Domain": "www.theinformationlab.co.uk", "[Amplitude] Page Path": "/community/blog/using-dynamic-zone-visibility-for-show-hide-buttons/", "[Amplitude] Page Title": "Using Dynamic Zone Visibility for Show/Hide Buttons - The Information Lab", "[Amplitude] Page Location": "https://www.theinformationlab.co.uk/community/blog/using-dynamic-zone-visibility-for-show-hide-buttons/"}, "event_time": "2026-04-29 22:04:24.596000", "event_type": "[Amplitude] Page Viewed", "global_user_properties": null, "group_properties": {}, "groups": {}, "idfa": null, "ip_address": "209.129.115.6", "is_attribution_event": null, "language": "English", "library": "amplitude-ts/2.16.1", "location_lat": null, "location_lng": null, "os_name": "Chrome", "os_version": "147", "partner_id": null, "paying": null, "plan": {}, "platform": "Web", "processed_time": "2026-04-29 22:04:27.775000", "region": "California", "sample_rate": null, "server_received_time": "2026-04-29 22:04:26.209000", "server_upload_time": "2026-04-29 22:04:26.214000", "session_id": 1777500264586, "source_id": null, "start_version": null, "user_creation_time": null, "user_id": null, "user_properties": {"initial_utm_medium": "EMPTY", "initial_referring_domain": "EMPTY", "initial_utm_content": "EMPTY", "initial_utm_campaign": "EMPTY", "initial_li_fat_id": "EMPTY", "initial_twclid": "EMPTY", "initial_gclid": "EMPTY", "initial_utm_source": "EMPTY", "initial_dclid": "EMPTY", "initial_wbraid": "EMPTY", "initial_fbclid": "EMPTY", "initial_rtd_cid": "EMPTY", "initial_utm_id": "EMPTY", "initial_referrer": "EMPTY", "initial_gbraid": "EMPTY", "initial_utm_term": "EMPTY", "initial_msclkid": "EMPTY", "initial_ttclid": "EMPTY", "initial_ko_click_id": "EMPTY"}, "uuid": "dcc61170-6d0b-4861-b649-3a35bec42898", "version_name": null}, {"$insert_id": "a2863e8e-3245-4dbb-9c5a-2bf2c656101f", "$insert_key": null, "$schema": null, "adid": null, "amplitude_attribution_ids": null, "amplitude_event_type": null, "amplitude_id": 112055801661, "app": 100011471, "city": "Canton", "client_event_time": "2026-04-29 22:41:24.746000", "client_upload_time": "2026-04-29 22:41:25.873000", "country": "United States", "data": {"path": "/2/httpapi", "group_first_event": {}, "group_ids": {}}, "data_type": "event", "device_brand": null, "device_carrier": null, "device_family": "Windows", "device_id": "ca5361c6-00a8-4861-9664-c06b74e4fd56", "device_manufacturer": null, "device_model": null, "device_type": "Windows", "dma": "Boston, MA-Manchester, NH", "event_id": 5, "event_properties": {"[Amplitude] Page URL": "https://www.theinformationlab.co.uk/community/blog/creating-a-family-tree-in-tableau/", "referrer": "https://www.theinformationlab.co.uk/2020/11/18/creating-a-family-tree-in-tableau/", "[Amplitude] Page Counter": 1, "[Amplitude] Page Domain": "www.theinformationlab.co.uk", "[Amplitude] Page Path": "/community/blog/creating-a-family-tree-in-tableau/", "[Amplitude] Page Title": "Creating a Family Tree in Tableau - The Information Lab", "[Amplitude] Session Replay ID": "ca5361c6-00a8-4861-9664-c06b74e4fd56/1777502484740", "[Amplitude] Page Location": "https://www.theinformationlab.co.uk/community/blog/creating-a-family-tree-in-tableau/", "referring_domain": "www.theinformationlab.co.uk"}, "event_time": "2026-04-29 22:41:24.746000", "event_type": "[Amplitude] Page Viewed", "global_user_properties": null, "group_properties": {}, "groups": {}, "idfa": null, "ip_address": "108.7.36.197", "is_attribution_event": null, "language": "English", "library": "amplitude-ts/2.16.1", "location_lat": null, "location_lng": null, "os_name": "Chrome", "os_version": "147", "partner_id": null, "paying": null, "plan": {}, "platform": "Web", "processed_time": "2026-04-29 22:41:27.284000", "region": "Massachusetts", "sample_rate": null, "server_received_time": "2026-04-29 22:41:25.873000", "server_upload_time": "2026-04-29 22:41:25.878000", "session_id": 1777502484740, "source_id": null, "start_version": null, "user_creation_time": null, "user_id": null, "user_properties": {"initial_utm_medium": "EMPTY", "initial_referring_domain": "www.google.com", "initial_utm_content": "EMPTY", "initial_utm_campaign": "EMPTY", "initial_twclid": "EMPTY", "initial_li_fat_id": "EMPTY", "referrer": "https://www.google.com/", "initial_gclid": "EMPTY", "initial_utm_source": "EMPTY", "initial_dclid": "EMPTY", "initial_wbraid": "EMPTY", "initial_fbclid": "EMPTY", "initial_rtd_cid": "EMPTY", "initial_utm_id": "EMPTY", "initial_referrer": "https://www.google.com/", "initial_gbraid": "EMPTY", "initial_utm_term": "EMPTY", "initial_msclkid": "EMPTY", "initial_ttclid": "EMPTY", "initial_ko_click_id": "EMPTY", "referring_domain": "www.google.com"}, "uuid": "a7a31ec2-00cb-43c2-bac7-af691ebdeac4", "version_name": null}, {"$insert_id": "efcfe439-d2bb-43eb-9e26-0b61d0131894", "$insert_key": null, "$schema": null, "adid": null, "amplitude_attribution_ids": null, "amplitude_event_type": null, "amplitude_id": 112070188436, "app": 100011471, "city": "Brent", "client_event_time": "2026-04-29 22:40:44.440000", "client_upload_time": "2026-04-29 22:40:45.433000", "country": "United Kingdom", "data": {"path": "/2/httpapi", "group_first_event": {}, "group_ids": {}}, "data_type": "event", "device_brand": null, "device_carrier": null, "device_family": "Android", "device_id": "1e42471e-e8fe-442e-ab11-2ea405764c85", "device_manufacturer": null, "device_model": null, "device_type": "Android", "dma": null, "event_id": 1, "event_properties": {}, "event_time": "2026-04-29 22:40:44.440000", "event_type": "session_start", "global_user_properties": null, "group_properties": {}, "groups": {}, "idfa": null, "ip_address": "62.197.56.241", "is_attribution_event": null, "language": "English", "library": "amplitude-ts/2.16.1", "location_lat": null, "location_lng": null, "os_name": "Chrome Mobile", "os_version": "147", "partner_id": null, "paying": null, "plan": {}, "platform": "Web", "processed_time": "2026-04-29 22:40:46.405000", "region": "Brent", "sample_rate": null, "server_received_time": "2026-04-29 22:40:45.433000", "server_upload_time": "2026-04-29 22:40:45.435000", "session_id": 1777502444440, "source_id": null, "start_version": null, "user_creation_time": null, "user_id": null, "user_properties": {"initial_utm_medium": "EMPTY", "initial_referring_domain": "com.linkedin.android", "initial_utm_content": "EMPTY", "initial_utm_campaign": "EMPTY", "initial_li_fat_id": "EMPTY", "initial_twclid": "EMPTY", "referrer": "android-app://com.linkedin.android/", "initial_gclid": "EMPTY", "initial_utm_source": "EMPTY", "initial_dclid": "EMPTY", "initial_wbraid": "EMPTY", "initial_fbclid": "EMPTY", "initial_rtd_cid": "EMPTY", "initial_utm_id": "EMPTY", "initial_referrer": "android-app://com.linkedin.android/", "initial_gbraid": "EMPTY", "initial_utm_term": "EMPTY", "initial_msclkid": "EMPTY", "initial_ttclid": "EMPTY", "initial_ko_click_id": "EMPTY", "referring_domain": "com.linkedin.android"}, "uuid": "c270666c-1f8f-46d1-94a9-91a216ebc11e", "version_name": null}, {"$insert_id": "7eeadd50-1b66-416f-b727-2d561e1eb362", "$insert_key": null, "$schema": null, "adid": null, "amplitude_attribution_ids": null, "amplitude_event_type": null, "amplitude_id": 112069231939, "app": 100011471, "city": null, "client_event_time": "2026-04-29 22:30:41.605000", "client_upload_time": "2026-04-29 22:30:44.369000", "country": "Singapore", "data": {"path": "/2/httpapi", "group_first_event": {}, "group_ids": {}}, "data_type": "event", "device_brand": null, "device_carrier": null, "device_family": "Windows", "device_id": "07bb1174-18c7-4c63-94bc-4265cfca28f3", "device_manufacturer": null, "device_model": null, "device_type": "Windows", "dma": null, "event_id": 1, "event_properties": {"[Amplitude] Session Replay ID": "07bb1174-18c7-4c63-94bc-4265cfca28f3/1777501841605"}, "event_time": "2026-04-29 22:30:41.605000", "event_type": "session_start", "global_user_properties": null, "group_properties": {}, "groups": {}, "idfa": null, "ip_address": "43.172.197.81", "is_attribution_event": null, "language": "English", "library": "amplitude-ts/2.16.1", "location_lat": null, "location_lng": null, "os_name": "Chrome", "os_version": "111", "partner_id": null, "paying": null, "plan": {}, "platform": "Web", "processed_time": "2026-04-29 22:30:46.778000", "region": null, "sample_rate": null, "server_received_time": "2026-04-29 22:30:44.369000", "server_upload_time": "2026-04-29 22:30:44.372000", "session_id": 1777501841605, "source_id": null, "start_version": null, "user_creation_time": null, "user_id": null, "user_properties": {"initial_utm_medium": "EMPTY", "initial_referring_domain": "EMPTY", "initial_utm_content": "EMPTY", "initial_utm_campaign": "EMPTY", "initial_li_fat_id": "EMPTY", "initial_twclid": "EMPTY", "initial_gclid": "EMPTY", "initial_utm_source": "EMPTY", "initial_dclid": "EMPTY", "initial_wbraid": "EMPTY", "initial_fbclid": "EMPTY", "initial_rtd_cid": "EMPTY", "initial_utm_id": "EMPTY", "initial_referrer": "EMPTY", "initial_gbraid": "EMPTY", "initial_utm_term": "EMPTY", "initial_msclkid": "EMPTY", "initial_ttclid": "EMPTY", "initial_ko_click_id": "EMPTY"}, "uuid": "1ace9997-d341-45eb-9700-f05bfcf9570a", "version_name": null}, {"$insert_id": "b61668c6-8f5e-47f2-8541-39da9d0d6318", "$insert_key": null, "$schema": null, "adid": null, "amplitude_attribution_ids": null, "amplitude_event_type": null, "amplitude_id": 112070188436, "app": 100011471, "city": "Brent", "client_event_time": "2026-04-29 22:40:44.454000", "client_upload_time": "2026-04-29 22:40:45.433000", "country": "United Kingdom", "data": {"path": "/2/httpapi", "group_first_event": {}, "group_ids": {}}, "data_type": "event", "device_brand": null, "device_carrier": null, "device_family": "Android", "device_id": "1e42471e-e8fe-442e-ab11-2ea405764c85", "device_manufacturer": null, "device_model": null, "device_type": "Android", "dma": null, "event_id": 2, "event_properties": {"[Amplitude] Page URL": "https://www.theinformationlab.co.uk/community/event/Global/2026/04/from-dashboards-to-decisions-building-effective-bi/", "referrer": "android-app://com.linkedin.android/", "[Amplitude] Page Counter": 1, "[Amplitude] Page Domain": "www.theinformationlab.co.uk", "[Amplitude] Page Path": "/community/event/Global/2026/04/from-dashboards-to-decisions-building-effective-bi/", "[Amplitude] Page Title": "From Dashboards to Decisions: Building Effective BI - The Information Lab", "[Amplitude] Page Location": "https://www.theinformationlab.co.uk/community/event/Global/2026/04/from-dashboards-to-decisions-building-effective-bi/", "referring_domain": "com.linkedin.android"}, "event_time": "2026-04-29 22:40:44.454000", "event_type": "[Amplitude] Page Viewed", "global_user_properties": null, "group_properties": {}, "groups": {}, "idfa": null, "ip_address": "62.197.56.241", "is_attribution_event": null, "language": "English", "library": "amplitude-ts/2.16.1", "location_lat": null, "location_lng": null, "os_name": "Chrome Mobile", "os_version": "147", "partner_id": null, "paying": null, "plan": {}, "platform": "Web", "processed_time": "2026-04-29 22:40:46.405000", "region": "Brent", "sample_rate": null, "server_received_time": "2026-04-29 22:40:45.433000", "server_upload_time": "2026-04-29 22:40:45.435000", "session_id": 1777502444440, "source_id": null, "start_version": null, "user_creation_time": null, "user_id": null, "user_properties": {"initial_utm_medium": "EMPTY", "initial_referring_domain": "com.linkedin.android", "initial_utm_content": "EMPTY", "initial_utm_campaign": "EMPTY", "initial_li_fat_id": "EMPTY", "initial_twclid": "EMPTY", "referrer": "android-app://com.linkedin.android/", "initial_gclid": "EMPTY", "initial_utm_source": "EMPTY", "initial_dclid": "EMPTY", "initial_wbraid": "EMPTY", "initial_fbclid": "EMPTY", "initial_rtd_cid": "EMPTY", "initial_utm_id": "EMPTY", "initial_referrer": "android-app://com.linkedin.android/", "initial_gbraid": "EMPTY", "initial_utm_term": "EMPTY", "initial_msclkid": "EMPTY", "initial_ttclid": "EMPTY", "initial_ko_click_id": "EMPTY", "referring_domain": "com.linkedin.android"}, "uuid": "b9d6d4ae-410f-4cc8-ae11-1b57ff96346b", "version_name": null}, {"$insert_id": "72cc6a0f-d754-4399-b482-127366a051a3", "$insert_key": null, "$schema": null, "adid": null, "amplitude_attribution_ids": null, "amplitude_event_type": null, "amplitude_id": 112070188436, "app": 100011471, "city": "Brent", "client_event_time": "2026-04-29 22:40:51.491000", "client_upload_time": "2026-04-29 22:40:52.791000", "country": "United Kingdom", "data": {"path": "/2/httpapi", "group_first_event": {}, "group_ids": {}}, "data_type": "event", "device_brand": null, "device_carrier": null, "device_family": "Android", "device_id": "1e42471e-e8fe-442e-ab11-2ea405764c85", "device_manufacturer": null, "device_model": null, "device_type": "Android", "dma": null, "event_id": 3, "event_properties": {"[Amplitude] Page URL": "https://www.theinformationlab.co.uk/community/event/Global/2026/04/from-dashboards-to-decisions-building-effective-bi/", "[Amplitude] Element Position Left": 20, "[Amplitude] Element Href": "https://events.zoom.us/ev/AqiysJ_glJZXgH-0v3mqL5pgevTnkd2oosGHi2omj-nzDJwOu_9l~AhaD5-YCLscGzFJCcjRL_BZSzUxXnrizDFzQYH4OCDza2hzj158BipCOLH4Fb56JLtWrHqSc_JnJoqun6Q7XFEmKxg", "[Amplitude] Element Hierarchy": [{"classes": ["ctabtn", "rounded-full", "transition", "cursor-pointer", "bg-blue-700", "hover:bg-blue-900", "text-white", "uppercase", "font-title", "tracking-[0.04em]", "text-sm", "w-full", "lg:w-auto", "h-10", "inline-flex", "items-center", "justify-center", "px-8"], "index": 0, "tag": "a", "indexOfType": 0, "attrs": {"href": "https://events.zoom.us/ev/AqiysJ_glJZXgH-0v3mqL5pgevTnkd2oosGHi2omj-nzDJwOu_9l~AhaD5-YCLscGzFJCcjRL_BZSzUxXnrizDFzQYH4OCDza2hzj1", "target": "_blank"}}, {"index": 0, "tag": "div", "indexOfType": 0}, {"classes": ["mt-4"], "index": 0, "tag": "div", "indexOfType": 0}, {"prevSib": "div", "classes": ["lg:hidden", "mb-6", "lg:mb-0", "md:flex", "gap-4"], "index": 1, "tag": "div", "indexOfType": 1}, {"classes": ["max-w-[780px]", "mx-auto"], "index": 0, "tag": "div", "indexOfType": 0}, {"classes": ["mx-5", "col-span-3"], "index": 0, "tag": "div", "indexOfType": 0}], "[Amplitude] Element Tag": "a", "[Amplitude] Element Position Top": 368, "[Amplitude] Element Parent Label": "From Dashboards to Decisions: Building Effective BI", "[Amplitude] Page Title": "From Dashboards to Decisions: Building Effective BI - The Information Lab", "[Amplitude] Element Class": "ctabtn rounded-full transition cursor-pointer\n                    bg-blue-700 hover:bg-blue-900 text-white \n                    uppercase font-title tracking-[0.04em] text-sm w-full lg:w-auto h-10 inline-flex items-center justify-center \n                    px-8", "[Amplitude] Element Text": "Register Here", "[Amplitude] Viewport Height": 764, "[Amplitude] Viewport Width": 360}, "event_time": "2026-04-29 22:40:51.491000", "event_type": "[Amplitude] Element Clicked", "global_user_properties": null, "group_properties": {}, "groups": {}, "idfa": null, "ip_address": "62.197.56.241", "is_attribution_event": null, "language": "English", "library": "amplitude-ts/2.16.1", "location_lat": null, "location_lng": null, "os_name": "Chrome Mobile", "os_version": "147", "partner_id": null, "paying": null, "plan": {}, "platform": "Web", "processed_time": "2026-04-29 22:40:54.423000", "region": "Brent", "sample_rate": null, "server_received_time": "2026-04-29 22:40:52.791000", "server_upload_time": "2026-04-29 22:40:52.795000", "session_id": 1777502444440, "source_id": null, "start_version": null, "user_creation_time": null, "user_id": null, "user_properties": {"initial_utm_medium": "EMPTY", "initial_referring_domain": "com.linkedin.android", "initial_utm_content": "EMPTY", "initial_utm_campaign": "EMPTY", "initial_twclid": "EMPTY", "initial_li_fat_id": "EMPTY", "referrer": "android-app://com.linkedin.android/", "initial_gclid": "EMPTY", "initial_utm_source": "EMPTY", "initial_dclid": "EMPTY", "initial_wbraid": "EMPTY", "initial_fbclid": "EMPTY", "initial_rtd_cid": "EMPTY", "initial_utm_id": "EMPTY", "initial_referrer": "android-app://com.linkedin.android/", "initial_gbraid": "EMPTY", "initial_utm_term": "EMPTY", "initial_msclkid": "EMPTY", "initial_ttclid": "EMPTY", "initial_ko_click_id": "EMPTY", "referring_domain": "com.linkedin.android"}, "uuid": "8e4db7f6-7c3e-4777-b259-521b51cb1e37", "version_name": null}, {"$insert_id": "18a3710d-57ad-489d-8afa-f73ac4e75573", "$insert_key": null, "$schema": null, "adid": null, "amplitude_attribution_ids": null, "amplitude_event_type": null, "amplitude_id": 112069231939, "app": 100011471, "city": null, "client_event_time": "2026-04-29 22:30:41.609000", "client_upload_time": "2026-04-29 22:31:48.739000", "country": "Singapore", "data": {"path": "/batch", "user_properties_updated": true, "group_first_event": {}, "group_ids": {}}, "data_type": "event", "device_brand": null, "device_carrier": null, "device_family": "Windows", "device_id": "07bb1174-18c7-4c63-94bc-4265cfca28f3", "device_manufacturer": null, "device_model": null, "device_type": "Windows", "dma": null, "event_id": 0, "event_properties": {"[Amplitude] Session Replay ID": "07bb1174-18c7-4c63-94bc-4265cfca28f3/1777501841605", "[Amplitude] Session Replay Library": "plugin/1.16.1"}, "event_time": "2026-04-29 22:30:41.609000", "event_type": "[Amplitude] Replay Captured", "global_user_properties": null, "group_properties": {}, "groups": {}, "idfa": null, "ip_address": "43.172.197.81", "is_attribution_event": null, "language": "English", "library": "amplitude-java/1.10.3", "location_lat": 0.0, "location_lng": 0.0, "os_name": "Chrome", "os_version": "111", "partner_id": null, "paying": null, "plan": {}, "platform": "Web", "processed_time": "2026-04-29 22:31:49.582000", "region": null, "sample_rate": null, "server_received_time": "2026-04-29 22:31:48.739000", "server_upload_time": "2026-04-29 22:31:48.743000", "session_id": 1777501841605, "source_id": null, "start_version": null, "user_creation_time": null, "user_id": null, "user_properties": {"initial_utm_medium": "EMPTY", "initial_referring_domain": "EMPTY", "initial_utm_content": "EMPTY", "initial_utm_campaign": "EMPTY", "initial_twclid": "EMPTY", "initial_li_fat_id": "EMPTY", "initial_gclid": "EMPTY", "initial_utm_source": "EMPTY", "initial_dclid": "EMPTY", "initial_wbraid": "EMPTY", "initial_fbclid": "EMPTY", "initial_rtd_cid": "EMPTY", "initial_utm_id": "EMPTY", "initial_referrer": "EMPTY", "initial_gbraid": "EMPTY", "initial_utm_term": "EMPTY", "initial_msclkid": "EMPTY", "initial_ttclid": "EMPTY", "initial_ko_click_id": "EMPTY"}, "uuid": "8b84252d-13b9-48c9-9d55-b10fb107f280", "version_name": null}, {"$insert_id": "bfc0f6a4-f867-410c-8d5c-129f60cdd2bb", "$insert_key": null, "$schema": null, "adid": null, "amplitude_attribution_ids": null, "amplitude_event_type": null, "amplitude_id": 112055801661, "app": 100011471, "city": "Canton", "client_event_time": "2026-04-29 22:41:24.762000", "client_upload_time": "2026-04-29 22:41:48.522000", "country": "United States", "data": {"path": "/batch", "user_properties_updated": true, "group_first_event": {}, "group_ids": {}}, "data_type": "event", "device_brand": null, "device_carrier": null, "device_family": "Windows", "device_id": "ca5361c6-00a8-4861-9664-c06b74e4fd56", "device_manufacturer": null, "device_model": null, "device_type": "Windows", "dma": "Boston, MA-Manchester, NH", "event_id": 0, "event_properties": {"[Amplitude] Session Replay ID": "ca5361c6-00a8-4861-9664-c06b74e4fd56/1777502484740", "[Amplitude] Session Replay Library": "plugin/1.16.1"}, "event_time": "2026-04-29 22:41:24.762000", "event_type": "[Amplitude] Replay Captured", "global_user_properties": null, "group_properties": {}, "groups": {}, "idfa": null, "ip_address": "108.7.36.197", "is_attribution_event": null, "language": "English", "library": "amplitude-java/1.10.3", "location_lat": 0.0, "location_lng": 0.0, "os_name": "Chrome", "os_version": "147", "partner_id": null, "paying": null, "plan": {}, "platform": "Web", "processed_time": "2026-04-29 22:41:48.941000", "region": "Massachusetts", "sample_rate": null, "server_received_time": "2026-04-29 22:41:48.522000", "server_upload_time": "2026-04-29 22:41:48.529000", "session_id": 1777502484740, "source_id": null, "start_version": null, "user_creation_time": null, "user_id": null, "user_properties": {"initial_utm_medium": "EMPTY", "initial_referring_domain": "www.google.com", "initial_utm_content": "EMPTY", "initial_utm_campaign": "EMPTY", "initial_twclid": "EMPTY", "initial_li_fat_id": "EMPTY", "referrer": "https://www.google.com/", "initial_gclid": "EMPTY", "initial_utm_source": "EMPTY", "initial_dclid": "EMPTY", "initial_wbraid": "EMPTY", "initial_fbclid": "EMPTY", "initial_rtd_cid": "EMPTY", "initial_utm_id": "EMPTY", "initial_referrer": "https://www.google.com/", "initial_gbraid": "EMPTY", "initial_utm_term": "EMPTY", "initial_msclkid": "EMPTY", "initial_ttclid": "EMPTY", "initial_ko_click_id": "EMPTY", "referring_domain": "www.google.com"}, "uuid": "d923c80f-b66a-4e58-9797-b85305df5e13", "version_name": null}, {"$insert_id": "951ffbce-1fc6-493c-99ca-e2bff041704d", "$insert_key": null, "$schema": null, "adid": null, "amplitude_attribution_ids": null, "amplitude_event_type": null, "amplitude_id": 112067421605, "app": 100011471, "city": "Seattle", "client_event_time": "2026-04-29 22:16:04.178000", "client_upload_time": "2026-04-29 22:16:06.147000", "country": "United States", "data": {"path": "/2/httpapi", "group_first_event": {}, "group_ids": {}}, "data_type": "event", "device_brand": null, "device_carrier": null, "device_family": "Mac OS X", "device_id": "2c23a349-2ad8-4aa0-bc4b-aceab1c58016", "device_manufacturer": null, "device_model": null, "device_type": "Mac", "dma": "Seattle-Tacoma, WA", "event_id": 1, "event_properties": {}, "event_time": "2026-04-29 22:16:04.178000", "event_type": "session_start", "global_user_properties": null, "group_properties": {}, "groups": {}, "idfa": null, "ip_address": "172.224.243.16", "is_attribution_event": null, "language": "English", "library": "amplitude-ts/2.16.1", "location_lat": null, "location_lng": null, "os_name": "Safari", "os_version": "26", "partner_id": null, "paying": null, "plan": {}, "platform": "Web", "processed_time": "2026-04-29 22:16:08.238000", "region": "Washington", "sample_rate": null, "server_received_time": "2026-04-29 22:16:06.147000", "server_upload_time": "2026-04-29 22:16:06.149000", "session_id": 1777500964178, "source_id": null, "start_version": null, "user_creation_time": null, "user_id": null, "user_properties": {"initial_utm_medium": "EMPTY", "initial_referring_domain": "www.google.com", "initial_utm_content": "EMPTY", "initial_utm_campaign": "EMPTY", "initial_li_fat_id": "EMPTY", "initial_twclid": "EMPTY", "referrer": "https://www.google.com/", "initial_gclid": "EMPTY", "initial_utm_source": "EMPTY", "initial_dclid": "EMPTY", "initial_wbraid": "EMPTY", "initial_fbclid": "EMPTY", "initial_rtd_cid": "EMPTY", "initial_utm_id": "EMPTY", "initial_referrer": "https://www.google.com/", "initial_gbraid": "EMPTY", "initial_utm_term": "EMPTY", "initial_msclkid": "EMPTY", "initial_ttclid": "EMPTY", "initial_ko_click_id": "EMPTY", "referring_domain": "www.google.com"}, "uuid": "f2087af4-1655-4857-abce-743ec269f92d", "version_name": null}, {"$insert_id": "621ee02e-7eaa-4257-9411-91181618ac59", "$insert_key": null, "$schema": null, "adid": null, "amplitude_attribution_ids": null, "amplitude_event_type": null, "amplitude_id": 112069231939, "app": 100011471, "city": null, "client_event_time": "2026-04-29 22:30:42.195000", "client_upload_time": "2026-04-29 22:30:44.369000", "country": "Singapore", "data": {"path": "/2/httpapi", "group_first_event": {}, "group_ids": {}}, "data_type": "event", "device_brand": null, "device_carrier": null, "device_family": "Windows", "device_id": "07bb1174-18c7-4c63-94bc-4265cfca28f3", "device_manufacturer": null, "device_model": null, "device_type": "Windows", "dma": null, "event_id": 2, "event_properties": {"[Amplitude] Page URL": "https://www.theinformationlab.co.uk/community/blog/translate-foreign-language-text-alteryx/", "[Amplitude] Page Counter": 1, "[Amplitude] Page Domain": "www.theinformationlab.co.uk", "[Amplitude] Page Path": "/community/blog/translate-foreign-language-text-alteryx/", "[Amplitude] Page Title": "How to Translate Foreign Language Text with Alteryx - The Information Lab", "[Amplitude] Session Replay ID": "07bb1174-18c7-4c63-94bc-4265cfca28f3/1777501841605", "[Amplitude] Page Location": "https://www.theinformationlab.co.uk/community/blog/translate-foreign-language-text-alteryx/"}, "event_time": "2026-04-29 22:30:42.195000", "event_type": "[Amplitude] Page Viewed", "global_user_properties": null, "group_properties": {}, "groups": {}, "idfa": null, "ip_address": "43.172.197.81", "is_attribution_event": null, "language": "English", "library": "amplitude-ts/2.16.1", "location_lat": null, "location_lng": null, "os_name": "Chrome", "os_version": "111", "partner_id": null, "paying": null, "plan": {}, "platform": "Web", "processed_time": "2026-04-29 22:30:46.778000", "region": null, "sample_rate": null, "server_received_time": "2026-04-29 22:30:44.369000", "server_upload_time": "2026-04-29 22:30:44.372000", "session_id": 1777501841605, "source_id": null, "start_version": null, "user_creation_time": null, "user_id": null, "user_properties": {"initial_utm_medium": "EMPTY", "initial_referring_domain": "EMPTY", "initial_utm_content": "EMPTY", "initial_utm_campaign": "EMPTY", "initial_li_fat_id": "EMPTY", "initial_twclid": "EMPTY", "initial_gclid": "EMPTY", "initial_utm_source": "EMPTY", "initial_dclid": "EMPTY", "initial_wbraid": "EMPTY", "initial_fbclid": "EMPTY", "initial_rtd_cid": "EMPTY", "initial_utm_id": "EMPTY", "initial_referrer": "EMPTY", "initial_gbraid": "EMPTY", "initial_utm_term": "EMPTY", "initial_msclkid": "EMPTY", "initial_ttclid": "EMPTY", "initial_ko_click_id": "EMPTY"}, "uuid": "f3ab8198-2f9d-42fe-8971-2b1c76bf14c7", "version_name": null}, {"$insert_id": "5fb25368-61ce-48e8-a8bf-dc0cd22e1204", "$insert_key": null, "$schema": null, "adid": null, "amplitude_attribution_ids": null, "amplitude_event_type": null, "amplitude_id": 112067421605, "app": 100011471, "city": "Seattle", "client_event_time": "2026-04-29 22:16:04.187000", "client_upload_time": "2026-04-29 22:16:06.147000", "country": "United States", "data": {"path": "/2/httpapi", "group_first_event": {}, "group_ids": {}}, "data_type": "event", "device_brand": null, "device_carrier": null, "device_family": "Mac OS X", "device_id": "2c23a349-2ad8-4aa0-bc4b-aceab1c58016", "device_manufacturer": null, "device_model": null, "device_type": "Mac", "dma": "Seattle-Tacoma, WA", "event_id": 2, "event_properties": {"[Amplitude] Page URL": "https://www.theinformationlab.co.uk/community/blog/faster-faster-designing-for-performance-the-tools/", "referrer": "https://www.google.com/", "[Amplitude] Page Counter": 1, "[Amplitude] Page Domain": "www.theinformationlab.co.uk", "[Amplitude] Page Path": "/community/blog/faster-faster-designing-for-performance-the-tools/", "[Amplitude] Page Title": "Faster, Faster! Designing for Performance: the tools - The Information Lab", "[Amplitude] Page Location": "https://www.theinformationlab.co.uk/community/blog/faster-faster-designing-for-performance-the-tools/", "referring_domain": "www.google.com"}, "event_time": "2026-04-29 22:16:04.187000", "event_type": "[Amplitude] Page Viewed", "global_user_properties": null, "group_properties": {}, "groups": {}, "idfa": null, "ip_address": "172.224.243.16", "is_attribution_event": null, "language": "English", "library": "amplitude-ts/2.16.1", "location_lat": null, "location_lng": null, "os_name": "Safari", "os_version": "26", "partner_id": null, "paying": null, "plan": {}, "platform": "Web", "processed_time": "2026-04-29 22:16:08.238000", "region": "Washington", "sample_rate": null, "server_received_time": "2026-04-29 22:16:06.147000", "server_upload_time": "2026-04-29 22:16:06.149000", "session_id": 1777500964178, "source_id": null, "start_version": null, "user_creation_time": null, "user_id": null, "user_properties": {"initial_utm_medium": "EMPTY", "initial_referring_domain": "www.google.com", "initial_utm_content": "EMPTY", "initial_utm_campaign": "EMPTY", "initial_li_fat_id": "EMPTY", "initial_twclid": "EMPTY", "referrer": "https://www.google.com/", "initial_gclid": "EMPTY", "initial_utm_source": "EMPTY", "initial_dclid": "EMPTY", "initial_wbraid": "EMPTY", "initial_fbclid": "EMPTY", "initial_rtd_cid": "EMPTY", "initial_utm_id": "EMPTY", "initial_referrer": "https://www.google.com/", "initial_gbraid": "EMPTY", "initial_utm_term": "EMPTY", "initial_msclkid": "EMPTY", "initial_ttclid": "EMPTY", "initial_ko_click_id": "EMPTY", "referring_domain": "www.google.com"}, "uuid": "bc7467b3-b0b9-46b6-ae77-c87db7b2dc47", "version_name": null}, {"$insert_id": "800737bd-20f1-4e43-be53-ab3ab5beb1ce", "$insert_key": null, "$schema": null, "adid": null, "amplitude_attribution_ids": null, "amplitude_event_type": null, "amplitude_id": 112067447385, "app": 100011471, "city": "Singapore", "client_event_time": "2026-04-29 22:16:18.674000", "client_upload_time": "2026-04-29 22:16:21.321000", "country": "Singapore", "data": {"path": "/2/httpapi", "group_first_event": {}, "group_ids": {}}, "data_type": "event", "device_brand": null, "device_carrier": null, "device_family": "Windows", "device_id": "006109b7-f6f5-45d0-bc17-ce9b9e1c6a57", "device_manufacturer": null, "device_model": null, "device_type": "Windows", "dma": null, "event_id": 1, "event_properties": {}, "event_time": "2026-04-29 22:16:18.674000", "event_type": "session_start", "global_user_properties": null, "group_properties": {}, "groups": {}, "idfa": null, "ip_address": "43.173.181.15", "is_attribution_event": null, "language": "English", "library": "amplitude-ts/2.16.1", "location_lat": null, "location_lng": null, "os_name": "Chrome", "os_version": "103", "partner_id": null, "paying": null, "plan": {}, "platform": "Web", "processed_time": "2026-04-29 22:16:22.561000", "region": null, "sample_rate": null, "server_received_time": "2026-04-29 22:16:21.321000", "server_upload_time": "2026-04-29 22:16:21.323000", "session_id": 1777500978674, "source_id": null, "start_version": null, "user_creation_time": null, "user_id": null, "user_properties": {"initial_utm_medium": "EMPTY", "initial_referring_domain": "EMPTY", "initial_utm_content": "EMPTY", "initial_utm_campaign": "EMPTY", "initial_li_fat_id": "EMPTY", "initial_twclid": "EMPTY", "initial_gclid": "EMPTY", "initial_utm_source": "EMPTY", "initial_dclid": "EMPTY", "initial_wbraid": "EMPTY", "initial_fbclid": "EMPTY", "initial_rtd_cid": "EMPTY", "initial_utm_id": "EMPTY", "initial_referrer": "EMPTY", "initial_gbraid": "EMPTY", "initial_utm_term": "EMPTY", "initial_msclkid": "EMPTY", "initial_ttclid": "EMPTY", "initial_ko_click_id": "EMPTY"}, "uuid": "173fd3b3-e761-4c57-a653-032c6eda6905", "version_name": null}, {"$insert_id": "fc48616a-ef86-4f6d-92cd-14aaa2204d74", "$insert_key": null, "$schema": null, "adid": null, "amplitude_attribution_ids": null, "amplitude_event_type": null, "amplitude_id": 112067447385, "app": 100011471, "city": "Singapore", "client_event_time": "2026-04-29 22:16:18.709000", "client_upload_time": "2026-04-29 22:16:21.321000", "country": "Singapore", "data": {"path": "/2/httpapi", "group_first_event": {}, "group_ids": {}}, "data_type": "event", "device_brand": null, "device_carrier": null, "device_family": "Windows", "device_id": "006109b7-f6f5-45d0-bc17-ce9b9e1c6a57", "device_manufacturer": null, "device_model": null, "device_type": "Windows", "dma": null, "event_id": 2, "event_properties": {"[Amplitude] Page URL": "https://www.theinformationlab.co.uk/", "[Amplitude] Page Counter": 1, "[Amplitude] Page Domain": "www.theinformationlab.co.uk", "[Amplitude] Page Path": "/", "[Amplitude] Page Title": "The Information Lab", "[Amplitude] Page Location": "https://www.theinformationlab.co.uk/"}, "event_time": "2026-04-29 22:16:18.709000", "event_type": "[Amplitude] Page Viewed", "global_user_properties": null, "group_properties": {}, "groups": {}, "idfa": null, "ip_address": "43.173.181.15", "is_attribution_event": null, "language": "English", "library": "amplitude-ts/2.16.1", "location_lat": null, "location_lng": null, "os_name": "Chrome", "os_version": "103", "partner_id": null, "paying": null, "plan": {}, "platform": "Web", "processed_time": "2026-04-29 22:16:22.562000", "region": null, "sample_rate": null, "server_received_time": "2026-04-29 22:16:21.321000", "server_upload_time": "2026-04-29 22:16:21.323000", "session_id": 1777500978674, "source_id": null, "start_version": null, "user_creation_time": null, "user_id": null, "user_properties": {"initial_utm_medium": "EMPTY", "initial_referring_domain": "EMPTY", "initial_utm_content": "EMPTY", "initial_utm_campaign": "EMPTY", "initial_li_fat_id": "EMPTY", "initial_twclid": "EMPTY", "initial_gclid": "EMPTY", "initial_utm_source": "EMPTY", "initial_dclid": "EMPTY", "initial_wbraid": "EMPTY", "initial_fbclid": "EMPTY", "initial_rtd_cid": "EMPTY", "initial_utm_id": "EMPTY", "initial_referrer": "EMPTY", "initial_gbraid": "EMPTY", "initial_utm_term": "EMPTY", "initial_msclkid": "EMPTY", "initial_ttclid": "EMPTY", "initial_ko_click_id": "EMPTY"}, "uuid": "259d9191-0c59-4563-94e0-2991dfacf4dc", "version_name": null}, {"$insert_id": "6730d252-b714-483f-b00f-a5ee5b315a8f", "$insert_key": null, "$schema": null, "adid": null, "amplitude_attribution_ids": null, "amplitude_event_type": null, "amplitude_id": 112069537833, "app": 100011471, "city": "Federal Way", "client_event_time": "2026-04-29 22:33:57.553000", "client_upload_time": "2026-04-29 22:33:59.427000", "country": "United States", "data": {"path": "/2/httpapi", "group_first_event": {}, "group_ids": {}}, "data_type": "event", "device_brand": null, "device_carrier": null, "device_family": "Windows", "device_id": "9055f93f-c90c-4393-94bc-c59dcc66d7ce", "device_manufacturer": null, "device_model": null, "device_type": "Windows", "dma": "Seattle-Tacoma, WA", "event_id": 1, "event_properties": {}, "event_time": "2026-04-29 22:33:57.553000", "event_type": "session_start", "global_user_properties": null, "group_properties": {}, "groups": {}, "idfa": null, "ip_address": "24.17.85.169", "is_attribution_event": null, "language": "English", "library": "amplitude-ts/2.16.1", "location_lat": null, "location_lng": null, "os_name": "Edge", "os_version": "147", "partner_id": null, "paying": null, "plan": {}, "platform": "Web", "processed_time": "2026-04-29 22:33:59.820000", "region": "Washington", "sample_rate": null, "server_received_time": "2026-04-29 22:33:59.427000", "server_upload_time": "2026-04-29 22:33:59.430000", "session_id": 1777502037553, "source_id": null, "start_version": null, "user_creation_time": null, "user_id": null, "user_properties": {"initial_utm_medium": "EMPTY", "initial_referring_domain": "www.google.com", "initial_utm_content": "EMPTY", "initial_utm_campaign": "EMPTY", "initial_li_fat_id": "EMPTY", "initial_twclid": "EMPTY", "referrer": "https://www.google.com/", "initial_gclid": "EMPTY", "initial_utm_source": "EMPTY", "initial_dclid": "EMPTY", "initial_wbraid": "EMPTY", "initial_fbclid": "EMPTY", "initial_rtd_cid": "EMPTY", "initial_utm_id": "EMPTY", "initial_referrer": "https://www.google.com/", "initial_gbraid": "EMPTY", "initial_utm_term": "EMPTY", "initial_msclkid": "EMPTY", "initial_ttclid": "EMPTY", "initial_ko_click_id": "EMPTY", "referring_domain": "www.google.com"}, "uuid": "3150c526-eeed-455a-85a5-0c20a899edbb", "version_name": null}, {"$insert_id": "3de172d3-5f69-4f83-b336-e901f0b078ab", "$insert_key": null, "$schema": null, "adid": null, "amplitude_attribution_ids": null, "amplitude_event_type": null, "amplitude_id": 112069537833, "app": 100011471, "city": "Federal Way", "client_event_time": "2026-04-29 22:33:57.561000", "client_upload_time": "2026-04-29 22:33:59.427000", "country": "United States", "data": {"path": "/2/httpapi", "group_first_event": {}, "group_ids": {}}, "data_type": "event", "device_brand": null, "device_carrier": null, "device_family": "Windows", "device_id": "9055f93f-c90c-4393-94bc-c59dcc66d7ce", "device_manufacturer": null, "device_model": null, "device_type": "Windows", "dma": "Seattle-Tacoma, WA", "event_id": 2, "event_properties": {"[Amplitude] Page URL": "https://www.theinformationlab.co.uk/community/blog/new-licensing-with-alteryx-one-what-you-need-to-know-1/", "referrer": "https://www.google.com/", "[Amplitude] Page Counter": 1, "[Amplitude] Page Domain": "www.theinformationlab.co.uk", "[Amplitude] Page Path": "/community/blog/new-licensing-with-alteryx-one-what-you-need-to-know-1/", "[Amplitude] Page Title": "New licensing with Alteryx One: What You Need to Know - The Information Lab", "[Amplitude] Page Location": "https://www.theinformationlab.co.uk/community/blog/new-licensing-with-alteryx-one-what-you-need-to-know-1/", "referring_domain": "www.google.com"}, "event_time": "2026-04-29 22:33:57.561000", "event_type": "[Amplitude] Page Viewed", "global_user_properties": null, "group_properties": {}, "groups": {}, "idfa": null, "ip_address": "24.17.85.169", "is_attribution_event": null, "language": "English", "library": "amplitude-ts/2.16.1", "location_lat": null, "location_lng": null, "os_name": "Edge", "os_version": "147", "partner_id": null, "paying": null, "plan": {}, "platform": "Web", "processed_time": "2026-04-29 22:33:59.820000", "region": "Washington", "sample_rate": null, "server_received_time": "2026-04-29 22:33:59.427000", "server_upload_time": "2026-04-29 22:33:59.430000", "session_id": 1777502037553, "source_id": null, "start_version": null, "user_creation_time": null, "user_id": null, "user_properties": {"initial_utm_medium": "EMPTY", "initial_referring_domain": "www.google.com", "initial_utm_content": "EMPTY", "initial_utm_campaign": "EMPTY", "initial_li_fat_id": "EMPTY", "initial_twclid": "EMPTY", "referrer": "https://www.google.com/", "initial_gclid": "EMPTY", "initial_utm_source": "EMPTY", "initial_dclid": "EMPTY", "initial_wbraid": "EMPTY", "initial_fbclid": "EMPTY", "initial_rtd_cid": "EMPTY", "initial_utm_id": "EMPTY", "initial_referrer": "https://www.google.com/", "initial_gbraid": "EMPTY", "initial_utm_term": "EMPTY", "initial_msclkid": "EMPTY", "initial_ttclid": "EMPTY", "initial_ko_click_id": "EMPTY", "referring_domain": "www.google.com"}, "uuid": "651c9e26-17ec-47f1-89d1-cfa55cb5110b", "version_name": null}, {"$insert_id": "b94f05fe-4291-4302-bb7d-b37878c79726", "$insert_key": null, "$schema": null, "adid": null, "amplitude_attribution_ids": null, "amplitude_event_type": null, "amplitude_id": 112069912689, "app": 100011471, "city": "Saint Paul", "client_event_time": "2026-04-29 22:37:47.951000", "client_upload_time": "2026-04-29 22:37:49.974000", "country": "United States", "data": {"path": "/2/httpapi", "group_first_event": {}, "group_ids": {}}, "data_type": "event", "device_brand": null, "device_carrier": null, "device_family": "Windows", "device_id": "8e29c7cd-5b7a-4c4d-a842-ce2bcd630c37", "device_manufacturer": null, "device_model": null, "device_type": "Windows", "dma": "Minneapolis-St. Paul, MN", "event_id": 1, "event_properties": {}, "event_time": "2026-04-29 22:37:47.951000", "event_type": "session_start", "global_user_properties": null, "group_properties": {}, "groups": {}, "idfa": null, "ip_address": "47.41.73.247", "is_attribution_event": null, "language": "English", "library": "amplitude-ts/2.16.1", "location_lat": null, "location_lng": null, "os_name": "Edge", "os_version": "147", "partner_id": null, "paying": null, "plan": {}, "platform": "Web", "processed_time": "2026-04-29 22:37:51.727000", "region": "Minnesota", "sample_rate": null, "server_received_time": "2026-04-29 22:37:49.974000", "server_upload_time": "2026-04-29 22:37:49.978000", "session_id": 1777502267951, "source_id": null, "start_version": null, "user_creation_time": null, "user_id": null, "user_properties": {"initial_utm_medium": "EMPTY", "initial_referring_domain": "www.bing.com", "initial_utm_content": "EMPTY", "initial_utm_campaign": "EMPTY", "initial_li_fat_id": "EMPTY", "initial_twclid": "EMPTY", "referrer": "https://www.bing.com/", "initial_gclid": "EMPTY", "initial_utm_source": "EMPTY", "initial_dclid": "EMPTY", "initial_wbraid": "EMPTY", "initial_fbclid": "EMPTY", "initial_rtd_cid": "EMPTY", "initial_utm_id": "EMPTY", "initial_referrer": "https://www.bing.com/", "initial_gbraid": "EMPTY", "initial_utm_term": "EMPTY", "initial_msclkid": "EMPTY", "initial_ttclid": "EMPTY", "initial_ko_click_id": "EMPTY", "referring_domain": "www.bing.com"}, "uuid": "d2bee788-bf1c-425b-93d3-f7ef25bb34a5", "version_name": null}, {"$insert_id": "364a6b47-ea06-4bc0-a2a1-78b30ae605b2", "$insert_key": null, "$schema": null, "adid": null, "amplitude_attribution_ids": null, "amplitude_event_type": null, "amplitude_id": 112069912689, "app": 100011471, "city": "Saint Paul", "client_event_time": "2026-04-29 22:37:47.964000", "client_upload_time": "2026-04-29 22:37:49.974000", "country": "United States", "data": {"path": "/2/httpapi", "group_first_event": {}, "group_ids": {}}, "data_type": "event", "device_brand": null, "device_carrier": null, "device_family": "Windows", "device_id": "8e29c7cd-5b7a-4c4d-a842-ce2bcd630c37", "device_manufacturer": null, "device_model": null, "device_type": "Windows", "dma": "Minneapolis-St. Paul, MN", "event_id": 2, "event_properties": {"[Amplitude] Page URL": "https://www.theinformationlab.co.uk/community/blog/is-ai-the-death-of-the-data-analyst/", "referrer": "https://www.bing.com/", "[Amplitude] Page Counter": 1, "[Amplitude] Page Domain": "www.theinformationlab.co.uk", "[Amplitude] Page Path": "/community/blog/is-ai-the-death-of-the-data-analyst/", "[Amplitude] Page Title": "Is AI The Death of the Data Analyst? - The Information Lab", "[Amplitude] Page Location": "https://www.theinformationlab.co.uk/community/blog/is-ai-the-death-of-the-data-analyst/", "referring_domain": "www.bing.com"}, "event_time": "2026-04-29 22:37:47.964000", "event_type": "[Amplitude] Page Viewed", "global_user_properties": null, "group_properties": {}, "groups": {}, "idfa": null, "ip_address": "47.41.73.247", "is_attribution_event": null, "language": "English", "library": "amplitude-ts/2.16.1", "location_lat": null, "location_lng": null, "os_name": "Edge", "os_version": "147", "partner_id": null, "paying": null, "plan": {}, "platform": "Web", "processed_time": "2026-04-29 22:37:51.727000", "region": "Minnesota", "sample_rate": null, "server_received_time": "2026-04-29 22:37:49.974000", "server_upload_time": "2026-04-29 22:37:49.978000", "session_id": 1777502267951, "source_id": null, "start_version": null, "user_creation_time": null, "user_id": null, "user_properties": {"initial_utm_medium": "EMPTY", "initial_referring_domain": "www.bing.com", "initial_utm_content": "EMPTY", "initial_utm_campaign": "EMPTY", "initial_li_fat_id": "EMPTY", "initial_twclid": "EMPTY", "referrer": "https://www.bing.com/", "initial_gclid": "EMPTY", "initial_utm_source": "EMPTY", "initial_dclid": "EMPTY", "initial_wbraid": "EMPTY", "initial_fbclid": "EMPTY", "initial_rtd_cid": "EMPTY", "initial_utm_id": "EMPTY", "initial_referrer": "https://www.bing.com/", "initial_gbraid": "EMPTY", "initial_utm_term": "EMPTY", "initial_msclkid": "EMPTY", "initial_ttclid": "EMPTY", "initial_ko_click_id": "EMPTY", "referring_domain": "www.bing.com"}, "uuid": "08ac67f4-aacf-4352-944e-bf2bc542d681", "version_name": null}, {"$insert_id": "1ffcc8cb-9f7f-43be-bf38-c7de8e043df2", "$insert_key": null, "$schema": null, "adid": null, "amplitude_attribution_ids": null, "amplitude_event_type": null, "amplitude_id": 112070916441, "app": 100011471, "city": "Chicago", "client_event_time": "2026-04-29 22:48:29.883000", "client_upload_time": "2026-04-29 22:48:31.416000", "country": "United States", "data": {"path": "/2/httpapi", "group_first_event": {}, "group_ids": {}}, "data_type": "event", "device_brand": null, "device_carrier": null, "device_family": "Windows", "device_id": "39b6c9fb-f4e3-4174-bfc8-125dd3e5265d", "device_manufacturer": null, "device_model": null, "device_type": "Windows", "dma": "Chicago, IL", "event_id": 1, "event_properties": {}, "event_time": "2026-04-29 22:48:29.883000", "event_type": "session_start", "global_user_properties": null, "group_properties": {}, "groups": {}, "idfa": null, "ip_address": "57.140.28.57", "is_attribution_event": null, "language": "English", "library": "amplitude-ts/2.16.1", "location_lat": null, "location_lng": null, "os_name": "Chrome", "os_version": "146", "partner_id": null, "paying": null, "plan": {}, "platform": "Web", "processed_time": "2026-04-29 22:48:33.049000", "region": "Illinois", "sample_rate": null, "server_received_time": "2026-04-29 22:48:31.416000", "server_upload_time": "2026-04-29 22:48:31.418000", "session_id": 1777502909883, "source_id": null, "start_version": null, "user_creation_time": null, "user_id": null, "user_properties": {"initial_utm_medium": "EMPTY", "initial_referring_domain": "www.google.com", "initial_utm_content": "EMPTY", "initial_utm_campaign": "EMPTY", "initial_li_fat_id": "EMPTY", "initial_twclid": "EMPTY", "referrer": "https://www.google.com/", "initial_gclid": "EMPTY", "initial_utm_source": "EMPTY", "initial_dclid": "EMPTY", "initial_wbraid": "EMPTY", "initial_fbclid": "EMPTY", "initial_rtd_cid": "EMPTY", "initial_utm_id": "EMPTY", "initial_referrer": "https://www.google.com/", "initial_gbraid": "EMPTY", "initial_utm_term": "EMPTY", "initial_msclkid": "EMPTY", "initial_ttclid": "EMPTY", "initial_ko_click_id": "EMPTY", "referring_domain": "www.google.com"}, "uuid": "85e2d467-0a09-4284-837a-b1aa93c0a4cc", "version_name": null}, {"$insert_id": "8e57da8b-1369-4dd3-9483-00dbcc16da4b", "$insert_key": null, "$schema": null, "adid": null, "amplitude_attribution_ids": null, "amplitude_event_type": null, "amplitude_id": 112070916441, "app": 100011471, "city": "Chicago", "client_event_time": "2026-04-29 22:48:29.894000", "client_upload_time": "2026-04-29 22:48:31.416000", "country": "United States", "data": {"path": "/2/httpapi", "group_first_event": {}, "group_ids": {}}, "data_type": "event", "device_brand": null, "device_carrier": null, "device_family": "Windows", "device_id": "39b6c9fb-f4e3-4174-bfc8-125dd3e5265d", "device_manufacturer": null, "device_model": null, "device_type": "Windows", "dma": "Chicago, IL", "event_id": 2, "event_properties": {"[Amplitude] Page URL": "https://www.theinformationlab.co.uk/community/blog/new-feature-in-tableau-prep-builder-2020-1-fixed-level-of-detail-expressions/", "referrer": "https://www.google.com/", "[Amplitude] Page Counter": 1, "[Amplitude] Page Domain": "www.theinformationlab.co.uk", "[Amplitude] Page Path": "/community/blog/new-feature-in-tableau-prep-builder-2020-1-fixed-level-of-detail-expressions/", "[Amplitude] Page Title": "New feature in Tableau Prep Builder 2020.1: Fixed Level of Detail expressions - The Information Lab", "[Amplitude] Page Location": "https://www.theinformationlab.co.uk/community/blog/new-feature-in-tableau-prep-builder-2020-1-fixed-level-of-detail-expressions/", "referring_domain": "www.google.com"}, "event_time": "2026-04-29 22:48:29.894000", "event_type": "[Amplitude] Page Viewed", "global_user_properties": null, "group_properties": {}, "groups": {}, "idfa": null, "ip_address": "57.140.28.57", "is_attribution_event": null, "language": "English", "library": "amplitude-ts/2.16.1", "location_lat": null, "location_lng": null, "os_name": "Chrome", "os_version": "146", "partner_id": null, "paying": null, "plan": {}, "platform": "Web", "processed_time": "2026-04-29 22:48:33.049000", "region": "Illinois", "sample_rate": null, "server_received_time": "2026-04-29 22:48:31.416000", "server_upload_time": "2026-04-29 22:48:31.418000", "session_id": 1777502909883, "source_id": null, "start_version": null, "user_creation_time": null, "user_id": null, "user_properties": {"initial_utm_medium": "EMPTY", "initial_referring_domain": "www.google.com", "initial_utm_content": "EMPTY", "initial_utm_campaign": "EMPTY", "initial_li_fat_id": "EMPTY", "initial_twclid": "EMPTY", "referrer": "https://www.google.com/", "initial_gclid": "EMPTY", "initial_utm_source": "EMPTY", "initial_dclid": "EMPTY", "initial_wbraid": "EMPTY", "initial_fbclid": "EMPTY", "initial_rtd_cid": "EMPTY", "initial_utm_id": "EMPTY", "initial_referrer": "https://www.google.com/", "initial_gbraid": "EMPTY", "initial_utm_term": "EMPTY", "initial_msclkid": "EMPTY", "initial_ttclid": "EMPTY", "initial_ko_click_id": "EMPTY", "referring_domain": "www.google.com"}, "uuid": "87ee6e92-6c08-49f2-9a2d-34de6bc7d150", "version_name": null}]